lps_gen.py
lpschedule_generator/__init__.py
lpschedule_generator/_version.py
lpschedule_generator/data/schedule.jinja2
lpschedule_generator/data/speakers.jinja2
lpschedule_generator-0.10.2.dist-info/COPYING
lpschedule_generator-0.10.2.dist-info/METADATA
lpschedule_generator-0.10.2.dist-info/WHEEL
lpschedule_generator-0.10.2.dist-info/entry_points.txt
lpschedule_generator-0.10.2.dist-info/top_level.txt
lpschedule_generator-0.10.2.dist-info/RECORD
